{
  "project_info": {
    "project_number": "960263285993",
    "project_id": "cmsc23-todo-app-adcordero",
    "storage_bucket": "cmsc23-todo-app-adcordero.appspot.com"
  },
  "client": [
    {
      "client_info": {
        "mobilesdk_app_id": "1:960263285993:android:38ea3f3f1e3a7ee5065478",
        "android_client_info": {
          "package_name": "com.example.week7_networking_discussion"
        }
      },
      "oauth_client": [
        {
          "client_id": "960263285993-0r8g33i3vmuheoo19a7pihuinddv1l34.apps.googleusercontent.com",
          "client_type": 3
        }
      ],
      "api_key": [
        {
          "current_key": "AIzaSyDIREkEjnuPL_05rT358wn1idMx6ElyHSM"
        }
      ],
      "services": {
        "appinvite_service": {
          "other_platform_oauth_client": [
            {
              "client_id": "960263285993-0r8g33i3vmuheoo19a7pihuinddv1l34.apps.googleusercontent.com",
              "client_type": 3
            }
          ]
        }
      }
    }
  ],
  "configuration_version": "1"
}